ukparliament/__init__.py
ukparliament/client.py
ukparliament/parties.py
ukparliament/resource.py
ukparliament-0.6.dist-info/LICENSE
ukparliament-0.6.dist-info/METADATA
ukparliament-0.6.dist-info/WHEEL
ukparliament-0.6.dist-info/top_level.txt
ukparliament-0.6.dist-info/RECORD
