Metadata-Version: 2.1
Name: ukparliament
Version: 0.6
Summary: UK Parliament API Client
Home-page: https://github.com/russss/ukparliament
Author: Russ Garrett
Author-email: russ@garrett.co.uk
License: MIT
Keywords: parliament democracy uk
Platform: UNKNOWN
Classifier: Development Status :: 3 - Alpha
Classifier: License :: OSI Approved :: MIT License
Classifier: Programming Language :: Python :: 3 :: Only
Requires-Dist: requests
Requires-Dist: python-dateutil (==2.5.3)
